./.gitignore
./LICENSE.txt
./PKG-INFO
./README.md
./build.sh
./publish.sh
./pyproject.toml
./whatsnew.txt
./.idea/.gitignore
./.idea/a2a-agentspeak-eclipse.iml
./.idea/misc.xml
./.idea/modules.xml
./.idea/vcs.xml
./.idea/workspace.xml
./.idea/inspectionProfiles/profiles_settings.xml
./a2a_agentspeak/__init__.py
./a2a_agentspeak/a2a_stdlib.py
./a2a_agentspeak/actions.py
./a2a_agentspeak/asp_build.py
./a2a_agentspeak/asp_message.py
./a2a_agentspeak/build_server.py
./a2a_agentspeak/check.py
./a2a_agentspeak/embedded_agent.py
./a2a_agentspeak/send_message.py
./a2a_agentspeak/content_codecs/__init__.py
./a2a_agentspeak/content_codecs/cold_repository_codec.py
./a2a_agentspeak/content_codecs/common.py
./a2a_agentspeak/content_codecs/hot_repository_codec.py
./a2a_agentspeak/content_codecs/python_agentspeak_codec.py
./cold_repository/__init__.py
./cold_repository/codec.py
./cold_repository/cold_repository_server.py
./cold_repository/context.py
./cold_repository/repository.py
./cold_repository/run_cold_repository_server.py
./doc/A2A-ACL-class-diagram-full.drawio.svg
./doc/A2A-ACL-class-diagram.drawio
./hot_repository/__init__.py
./hot_repository/codec.py
./hot_repository/context.py
./hot_repository/hot_repository_server.py
./hot_repository/mistral_selector_prompt.py
./hot_repository/repository.py
./hot_repository/run_hot_repository_server.py
./sample_agents/failing_ping/pingable.asi
./sample_agents/failing_ping/pingable.asl
./sample_agents/ping/pingable.asi
./sample_agents/ping/pingable.asl
./sample_agents/python_agents/translator/translator_agent.py
./sample_agents/python_agents/translator/translator_nl_to_bdi/mistral_config.py
./sample_agents/python_agents/translator/translator_nl_to_bdi/translator.py
./sample_agents/requirement_generators/bad_requirement_manager.asi
./sample_agents/requirement_generators/bad_requirement_manager.asl
./sample_agents/requirement_generators/llm_based_requirement_manager.asi
a2a_agentspeak-0.0.12.dist-info/METADATA
a2a_agentspeak-0.0.12.dist-info/WHEEL
a2a_agentspeak-0.0.12.dist-info/licenses/LICENSE.txt
a2a_agentspeak-0.0.12.dist-info/RECORD
