Metadata-Version: 2.4
Name: a2a-agentspeak
Version: 0.0.12
Summary: AgentSpeak agents on A2A/ACL protocol.
Project-URL: Homepage, https://gitlab.eclipse.org/eclipse-research-labs/mosaico-project/a2a-agentspeak
Author-email: Julien Cohen <Julien.Cohen@imt-atlantique.fr>, Massimo Tisi <Massimo.Tisi@imt-atlantique.fr>
Maintainer-email: Julien Cohen <Julien.Cohen@imt-atlantique.fr>, Massimo Tisi <Massimo.Tisi@imt-atlantique.fr>
License-Expression: GPL-3.0-only
License-File: LICENSE.txt
Requires-Python: >=3.12
Requires-Dist: a2a-acl==0.0.12
Requires-Dist: a2a-sdk[http-server]>=0.3.22
Requires-Dist: agentspeak>=0.2.2
Requires-Dist: uvicorn[standard]>=0.38.0
